{
  "url": "https://itsolver.zendesk.com/api/v2/views/53965546.json",
  "id": 53965546,
  "title": "Copy of Collection Point Referrals in the last 60 days",
  "active": false,
  "updated_at": "2017-03-20T01:40:04Z",
  "created_at": "2016-10-05T12:11:01Z",
  "position": 22,
  "execution": {
    "group_by": null,
    "group_order": "desc",
    "sort_by": "nice_id",
    "sort_order": "desc",
    "group": null,
    "sort": {
      "id": "ticket_id",
      "title": "ID",
      "order": "desc"
    },
    "columns": [
      {
        "id": "subject",
        "title": "Subject"
      },
      {
        "id": "requester",
        "title": "Requester"
      },
      {
        "id": 24375476,
        "title": "Suburb of requester",
        "type": "tagger",
        "url": "https://itsolver.zendesk.com/api/v2/ticket_fields/24375476.json"
      },
      {
        "id": "created",
        "title": "Requested"
      },
      {
        "id": "assignee",
        "title": "Assignee"
      }
    ],
    "fields": [
      {
        "id": "subject",
        "title": "Subject"
      },
      {
        "id": "requester",
        "title": "Requester"
      },
      {
        "id": "created",
        "title": "Requested"
      },
      {
        "id": "assignee",
        "title": "Assignee"
      }
    ],
    "custom_fields": [
      {
        "id": 24375476,
        "title": "Suburb of requester",
        "type": "tagger",
        "url": "https://itsolver.zendesk.com/api/v2/ticket_fields/24375476.json"
      }
    ]
  },
  "conditions": {
    "all": [
      {
        "field": "description_includes_word",
        "operator": "includes",
        "value": "staff_name"
      },
      {
        "field": "status",
        "operator": "is_not",
        "value": "new"
      },
      {
        "field": "NEW",
        "operator": "less_than",
        "value": "1440"
      }
    ],
    "any": []
  },
  "restriction": null,
  "raw_title": "Copy of Collection Point Referrals in the last 60 days"
}